{"stats":{"minecraft:killed_by":{"minecraft:creeper":7},"minecraft:picked_up":{"minecraft:splash_potion":2,"minecraft:end_rod":2},"minecraft:dropped":{"minecraft:end_rod":1},"minecraft:custom":{"minecraft:time_since_rest":294,"minecraft:crouch_one_cm":1137,"minecraft:play_time":33828,"minecraft:sprint_one_cm":135148,"minecraft:walk_one_cm":82873,"minecraft:damage_taken":2004,"minecraft:deaths":7,"minecraft:sneak_time":652,"minecraft:mob_kills":54,"minecraft:drop":1,"minecraft:damage_dealt_resisted":625,"minecraft:jump":937,"minecraft:minecart_one_cm":708,"minecraft:damage_dealt":10,"minecraft:leave_game":1,"minecraft:walk_on_water_one_cm":92,"minecraft:time_since_death":291,"minecraft:total_world_time":33828,"minecraft:climb_one_cm":922,"minecraft:damage_resisted":120,"minecraft:fall_one_cm":18464,"minecraft:fly_one_cm":431506,"minecraft:horse_one_cm":1746},"minecraft:used":{"minecraft:knowledge_book":96,"minecraft:diamond_chestplate":1,"minecraft:wooden_sword":4,"minecraft:iron_sword":53,"minecraft:splash_potion":2}},"DataVersion":3218}